{"generated_at":1430770697,"data":[{"tournament":"Australian Open","result":"F","defeated":"Yuki Bhambri, Marinko Matosevic, João Sousa, Grigor Dimitrov, Nick Kyrgios, Tomáš Berdych","lost_to":"Novak Djokovic"},{"tournament":"ABN AMRO World Tennis Tournament","result":"QF","defeated":"Nicolas Mahut, Vasek Pospisil","lost_to":"Gilles Simon"},{"tournament":"Dubai Duty Free Tennis Championships","result":"QF","defeated":"Gilles Müller, João Sousa","lost_to":"Borna Ćorić"},{"tournament":"BNP Paribas Open","result":"SF","defeated":"Vasek Pospisil, Philipp Kohlschreiber, Adrian Mannarino, Feliciano López","lost_to":"Novak Djokovic"},{"tournament":"Miami Open, presented by Itau","result":"F","defeated":"Donald Young, Santiago Giraldo, Kevin Anderson, Dominic Thiem, Tomáš Berdych","lost_to":"Novak Djokovic"},{"tournament":"BMW Open by FWU AG","result":"W","defeated":"Mischa Zverev, Lukáš Rosol, Roberto Bautista Agut, Philipp Kohlschreiber","lost_to":""},{"tournament":"Mutua Madrid Open"},{"tournament":"Internazionali BNL d'Italia"},{"tournament":"Roland Garros"},{"tournament":"Wimbledon"},{"tournament":"Rogers Cup"},{"tournament":"Western & Southern Open - Cincinnati"},{"tournament":"US Open"},{"tournament":"Shanghai Rolex Masters"},{"tournament":"Swiss Indoors Basel"},{"tournament":"BNP Paribas Masters"},{"tournament":"Barclays ATP World Tour Finals"}],"_id":"andy_murray_schedule","_rev":"8-8d34923bd2ca5b108ad7199f7e9207a5"}